CONTRIBUTING.md
MANIFEST.in
README.rst
setup.py
docs/HISTORY.txt
docs/LICENSE.GPL
docs/LICENSE.txt
eea/__init__.py
eea.converter.egg-info/PKG-INFO
eea.converter.egg-info/SOURCES.txt
eea.converter.egg-info/dependency_links.txt
eea.converter.egg-info/entry_points.txt
eea.converter.egg-info/namespace_packages.txt
eea.converter.egg-info/not-zip-safe
eea.converter.egg-info/requires.txt
eea.converter.egg-info/top_level.txt
eea/converter/README.txt
eea/converter/__init__.py
eea/converter/async.py
eea/converter/common.zcml
eea/converter/config.py
eea/converter/configure.zcml
eea/converter/convert.py
eea/converter/interfaces.py
eea/converter/job.py
eea/converter/plone.zcml
eea/converter/profiles.zcml
eea/converter/utils.py
eea/converter/version.txt
eea/converter/watermark.py
eea/converter/zope2.zcml
eea/converter/browser/__init__.py
eea/converter/browser/configure.zcml
eea/converter/browser/interfaces.py
eea/converter/browser/app/__init__.py
eea/converter/browser/app/download.py
eea/converter/browser/app/pdfview.py
eea/converter/browser/app/support.py
eea/converter/browser/zpt/pdf.body.pt
eea/converter/browser/zpt/pdf.cover.back.pt
eea/converter/browser/zpt/pdf.cover.pt
eea/converter/browser/zpt/pdf.disclaimer.pt
eea/converter/browser/zpt/pdf.footer.pt
eea/converter/browser/zpt/pdf.header.pt
eea/converter/browser/zpt/pdf.macro.pt
eea/converter/browser/zpt/pdf.toc.pt
eea/converter/docs/convert.txt
eea/converter/docs/coverimage.txt
eea/converter/docs/metaparser.txt
eea/converter/docs/metaupdater.txt
eea/converter/events/__init__.py
eea/converter/events/async.py
eea/converter/events/configure.zcml
eea/converter/events/interfaces.py
eea/converter/events/sync.py
eea/converter/locales/eea.pot
eea/converter/locales/update.sh
eea/converter/locales/bg/LC_MESSAGES/eea.po
eea/converter/locales/cs/LC_MESSAGES/eea.po
eea/converter/locales/da/LC_MESSAGES/eea.po
eea/converter/locales/de/LC_MESSAGES/eea.po
eea/converter/locales/el/LC_MESSAGES/eea.po
eea/converter/locales/en/LC_MESSAGES/eea.po
eea/converter/locales/es/LC_MESSAGES/eea.po
eea/converter/locales/et/LC_MESSAGES/eea.po
eea/converter/locales/eu/LC_MESSAGES/eea.po
eea/converter/locales/fi/LC_MESSAGES/eea.po
eea/converter/locales/fr/LC_MESSAGES/eea.po
eea/converter/locales/hu/LC_MESSAGES/eea.po
